pagination/__init__.py
pagination/pagination.py
discord_embeds_pagination-0.0.7.dist-info/LICENCE
discord_embeds_pagination-0.0.7.dist-info/METADATA
discord_embeds_pagination-0.0.7.dist-info/WHEEL
discord_embeds_pagination-0.0.7.dist-info/top_level.txt
discord_embeds_pagination-0.0.7.dist-info/RECORD
