Metadata-Version: 2.1
Name: discord-embeds-pagination
Version: 0.0.7
Summary: Pagination for embeds in discord.py bots
Home-page: https://github.com/omaxpy/discord-embeds-pagination
Author: omaxpy
Author-email: moukasland@gmail.com
Classifier: Programming Language :: Python :: 3
License-File: LICENCE
Requires-Dist: discord.py==2.4.0
